bayesnn/BayesianLinear.py
bayesnn/__init__.py
bayesnn/functionals.py
bayesnn/loss.py
bayesnn-0.1.0.dist-info/licenses/LICENSE
bayesnn-0.1.0.dist-info/METADATA
bayesnn-0.1.0.dist-info/WHEEL
bayesnn-0.1.0.dist-info/top_level.txt
bayesnn-0.1.0.dist-info/RECORD
