Metadata-Version: 2.4
Name: bayesnn
Version: 0.1.0
Summary: Bayesian neural network building blocks for PyTorch.
Author: Feridun Tutuncuoglu
Project-URL: Homepage, https://github.com/PandaThr/BayesianNN
Project-URL: Source, https://github.com/PandaThr/BayesianNN
Project-URL: Issues, https://github.com/PandaThr/BayesianNN/issues
Keywords: bayesian,neural-network,pytorch,variational-inference
Classifier: Programming Language :: Python :: 3
Classifier: Programming Language :: Python :: 3 :: Only
Classifier: Programming Language :: Python :: 3.8
Classifier: Programming Language :: Python :: 3.9
Classifier: Programming Language :: Python :: 3.10
Classifier: Programming Language :: Python :: 3.11
Classifier: Programming Language :: Python :: 3.12
Classifier: License :: OSI Approved :: MIT License
Classifier: Operating System :: OS Independent
Classifier: Topic :: Scientific/Engineering :: Artificial Intelligence
Requires-Python: >=3.8
License-File: LICENSE
Requires-Dist: torch>=1.13
Dynamic: license-file
